Metadata-Version: 1.0
Name: probability-and-distributions
Version: 0.2
Summary: Gaussian and Binomial distributions
Home-page: UNKNOWN
Author: Wesley Jeng
Author-email: UNKNOWN
License: UNKNOWN
Platform: UNKNOWN
